[
  {
    "ts": "2019-06-25T23:02:53.173Z",
    "level": "error",
    "error": {
      "originalError": {
        "name": "AccessTokenInvalid",
        "message": "{\n  \"status\": 403,\n  \"statusText\": \"Forbidden\",\n  \"message\": \"The access token you sent could not be found or is invalid.\",\n  \"details\": {},\n  \"request\": {\n    \"url\": \"https://api.contentful.com:443/spaces/k721jnxe76g2\",\n    \"headers\": {\n      \"Accept\": \"application/json, text/plain, */*\",\n      \"Content-Type\": \"application/vnd.contentful.management.v1+json\",\n      \"X-Contentful-User-Agent\": \"app contentful.import/7.4.2; feature library-import; sdk contentful-management.js/5.2.1; platform node.js/v8.10.0; os Linux/4.15.0-52-generic;\",\n      \"Authorization\": \"Bearer ..._7z58\",\n      \"user-agent\": \"node.js/v8.10.0\",\n      \"Accept-Encoding\": \"gzip\"\n    },\n    \"method\": \"get\"\n  },\n  \"requestId\": \"948fc23ea790f9560828417992026a3d\"\n}"
      },
      "data": {
        "status": 403,
        "statusText": "Forbidden",
        "message": "The access token you sent could not be found or is invalid.",
        "details": {},
        "request": {
          "url": "https://api.contentful.com:443/spaces/k721jnxe76g2",
          "headers": {
            "Accept": "application/json, text/plain, */*",
            "Content-Type": "application/vnd.contentful.management.v1+json",
            "X-Contentful-User-Agent": "app contentful.import/7.4.2; feature library-import; sdk contentful-management.js/5.2.1; platform node.js/v8.10.0; os Linux/4.15.0-52-generic;",
            "Authorization": "Bearer ..._7z58",
            "user-agent": "node.js/v8.10.0",
            "Accept-Encoding": "gzip"
          },
          "method": "get"
        },
        "requestId": "948fc23ea790f9560828417992026a3d"
      }
    }
  }
]
